PyDeepAI/__init__.py
PyDeepAI-0.2.0.dist-info/METADATA
PyDeepAI-0.2.0.dist-info/WHEEL
PyDeepAI-0.2.0.dist-info/top_level.txt
PyDeepAI-0.2.0.dist-info/RECORD
