Metadata-Version: 2.1
Name: PyDeepAI
Version: 0.2.0
Summary: Unofficial DeepAI python module
Home-page: UNKNOWN
Author: Mikhail Serebryakov a.k.a Zanga
Author-email: <rayman.channel@yandex.ru>
License: UNKNOWN
Keywords: python,api,image api,video api,requests,http
Platform: UNKNOWN
Classifier: Intended Audience :: Developers
Classifier: Programming Language :: Python :: 3
Classifier: Operating System :: Unix
Classifier: Operating System :: MacOS :: MacOS X
Classifier: Operating System :: Microsoft :: Windows
Requires-Dist: requests
